tolonteria/__init__.py
tolonteria/int_to_rom.py
tolonteria/rom_to_int.py
tonlonteria-0.0.1.dist-info/METADATA
tonlonteria-0.0.1.dist-info/WHEEL
tonlonteria-0.0.1.dist-info/top_level.txt
tonlonteria-0.0.1.dist-info/RECORD
