Metadata-Version: 2.1
Name: tonlonteria
Version: 0.0.1
Summary: My first Python package, please have merci with it
Author: Felipe Kautzmann
Author-email: <recuerdaesto@gmail.com>
Keywords: python,int to roman,rom to int
Classifier: Development Status :: 3 - Alpha
Classifier: Intended Audience :: Education
Classifier: Programming Language :: Python :: 2
Classifier: Programming Language :: Python :: 3
Classifier: Operating System :: MacOS :: MacOS X
Classifier: Operating System :: Microsoft :: Windows
